CHANGELOG.txt
LICENSE.txt
MANIFEST.in
README.txt
setup.py
my_first_package/__init__.py
my_first_package/functions.py
my_first_package/greet.py
mypackage.egg-info/SOURCES.txt
mypackage.egg-info/dependency_links.txt
mypackage.egg-info/top_level.txt
tests/test.py
zeynepgokturksfirstproject.egg-info/PKG-INFO
zeynepgokturksfirstproject.egg-info/SOURCES.txt
zeynepgokturksfirstproject.egg-info/dependency_links.txt
zeynepgokturksfirstproject.egg-info/top_level.txt