Metadata-Version: 2.1
Name: zeynepgokturksfirstproject
Version: 0.0.1
Summary: Testing installation of Package
Home-page: UNKNOWN
Author: Zeynep Gokturk
Author-email: h.zeynepgokturk@gmail.com
License: MIT
Keywords: first try
Platform: UNKNOWN
License-File: LICENSE.txt
